LICENCE.txt
MANIFEST.in
README.md
setup.cfg
setup.py
asks/__init__.py
asks/auth.py
asks/base_funcs.py
asks/cookie_utils.py
asks/errors.py
asks/http_utils.py
asks/req_structs.py
asks/request_object.py
asks/response_objects.py
asks/sessions.py
asks/utils.py
asks.egg-info/PKG-INFO
asks.egg-info/SOURCES.txt
asks.egg-info/dependency_links.txt
asks.egg-info/requires.txt
asks.egg-info/top_level.txt