Metadata-Version: 1.1
Name: asks
Version: 2.3.2
Summary: asks - async http
Home-page: https://github.com/theelous3/asks
Author: Mark Jameson - aka theelous3
Author-email: UNKNOWN
License: MIT
Platform: UNKNOWN
Classifier: Programming Language :: Python :: 3
Classifier: Framework :: Trio
Classifier: Intended Audience :: Developers
Classifier: License :: OSI Approved :: MIT License
Classifier: Programming Language :: Python :: 3 :: Only
Classifier: Topic :: Internet :: WWW/HTTP
